configmypy/__init__.py
configmypy/argparse_config.py
configmypy/bunch.py
configmypy/pipeline_config.py
configmypy/type_inference.py
configmypy/utils.py
configmypy/yaml_config.py
configmypy/tests/__init__.py
configmypy/tests/pytest_mock_fixtures.py
configmypy/tests/test_argparse_config.py
configmypy/tests/test_bunch.py
configmypy/tests/test_pipeline_config.py
configmypy/tests/test_utils.py
configmypy/tests/test_yaml_config.py
configmypy-0.2.0.dist-info/LICENSE
configmypy-0.2.0.dist-info/METADATA
configmypy-0.2.0.dist-info/WHEEL
configmypy-0.2.0.dist-info/top_level.txt
configmypy-0.2.0.dist-info/RECORD
