Metadata-Version: 2.1
Name: configmypy
Version: 0.2.0
Summary: Fast and easy configuration of Python projects.
Home-page: https://github.com/JeanKossaifi/configmypy
Author: Jean Kossaifi
Author-email: jean.kossaifi@gmail.com
License: Modified BSD
Download-URL: https://github.com/JeanKossaifi/configmypy/tarball/0.2.0
Platform: UNKNOWN
Classifier: Topic :: Scientific/Engineering
Classifier: License :: OSI Approved :: BSD License
Classifier: Programming Language :: Python :: 3
License-File: LICENSE
Requires-Dist: pytest
Requires-Dist: pytest-mock
Requires-Dist: ruamel.yaml
